{
  "phone_number": "+18649398981",
  "timestamp": "2025-08-21T22:20:33.397567",
  "call_duration": "completed",
  "status": "call_ended",
  "question_count": 0,
  "medical_report": "# PRE-VISIT MEDICAL INTAKE REPORT\n\n**Patient:** John | **Appointment:** 2025-02-25 | **Date:** 2025-08-21 22:20\n\n### Primary concern:\nLeg pain affecting mobility\n\n### History of Present Illness (HPI):\nStarted after helping neighbor move heavy furniture, Sharp, Down right leg, 9/10 when bad, Constant, worse in the evening\n\n### Relevant Medical History (from EHR):\nDiabetes, well controlled with medication\n\n### Medications (from EHR and interview):\nIbuprofen 400mg three times a day, but barely helps, Allergies: No allergies\n\n---\n*Report generated by AI medical intake specialist | Questions asked: 0 | Status: identification*",
  "raw_patient_data": {
    "name": "John",
    "appointment_date": "2025-02-25",
    "chief_complaint": "Leg pain affecting mobility",
    "history_of_present_illness": {
      "onset": "Started after helping neighbor move heavy furniture",
      "provocation": "",
      "quality": "Sharp",
      "radiation": "Down right leg",
      "severity": "9/10 when bad",
      "timing": "Constant, worse in the evening",
      "duration": ""
    },
    "review_of_systems": {
      "constitutional": "",
      "cardiovascular": "",
      "respiratory": "",
      "gastrointestinal": "",
      "musculoskeletal": "",
      "neurological": "",
      "psychiatric": "",
      "pertinent_negatives": []
    },
    "medications": "Ibuprofen 400mg three times a day, but barely helps",
    "allergies": "No allergies",
    "past_medical_history": "Diabetes, well controlled with medication",
    "social_history": "",
    "family_history": "",
    "additional_notes": ""
  },
  "report_type": "pre_visit_screening",
  "priority": "normal"
}